AUTHORS.rst
CONTRIBUTING.rst
HISTORY.rst
LICENSE
MANIFEST.in
README.rst
VERSION
setup.cfg
setup.py
docs/Makefile
docs/authors.rst
docs/conf.py
docs/contributing.rst
docs/history.rst
docs/index.rst
docs/installation.rst
docs/make.bat
docs/readme.rst
docs/usage.rst
requirements/ci.txt
requirements/prod.txt
requirements/test.txt
tests/__init__.py
tests/test_tiingo_news_api.py
tiingo_news_api/__init__.py
tiingo_news_api/tiingo_news_api.py
tiingo_news_api.egg-info/PKG-INFO
tiingo_news_api.egg-info/SOURCES.txt
tiingo_news_api.egg-info/dependency_links.txt
tiingo_news_api.egg-info/not-zip-safe
tiingo_news_api.egg-info/requires.txt
tiingo_news_api.egg-info/top_level.txt