Metadata-Version: 2.1
Name: tiingo-news-api
Version: 0.1.1
Summary: Simple python API wrapper for interacting with Tiingo endpoints
Home-page: https://gitlab.com/paul_armstrong/tiingo_news_api
Author: Paul Armstrong
Author-email: parmstrong@gitlab.com
License: MIT license
Keywords: tiingo_news_api
Platform: UNKNOWN
Classifier: Development Status :: 2 - Pre-Alpha
Classifier: Intended Audience :: Developers
Classifier: License :: OSI Approved :: MIT License
Classifier: Natural Language :: English
Classifier: Programming Language :: Python :: 3
Classifier: Programming Language :: Python :: 3.6
Classifier: Programming Language :: Python :: 3.7
Classifier: Programming Language :: Python :: 3.8
Requires-Python: >=3.6
License-File: LICENSE
License-File: AUTHORS.rst
